[
    {
        "user": "U06L4GLRAK1",
        "type": "message",
        "ts": "1726384971.767129",
        "client_msg_id": "4BABF122-6603-471A-98F8-2991FEC562B5",
        "text": "アウトレット行こ！！！",
        "team": "T06L90YHJF8",
        "user_team": "T06L90YHJF8",
        "source_team": "T06L90YHJF8",
        "user_profile": {
            "avatar_hash": "3fbda777c529",
            "image_72": "https:\/\/avatars.slack-edge.com\/2024-06-01\/7207571100146_3fbda777c529157f55d6_72.png",
            "first_name": "根本悠平",
            "real_name": "根本悠平",
            "display_name": "Nemoto.Yuhei",
            "team": "T06L90YHJF8",
            "name": "youpinggenben",
            "is_restricted": false,
            "is_ultra_restricted": false
        },
        "thread_ts": "1726382194.260959",
        "parent_user_id": "U06L9S67MEJ",
        "blocks": [
            {
                "type": "rich_text",
                "block_id": "eeBAV",
                "elements": [
                    {
                        "type": "rich_text_section",
                        "elements": [
                            {
                                "type": "text",
                                "text": "アウトレット行こ！！！"
                            }
                        ]
                    }
                ]
            }
        ],
        "reactions": [
            {
                "name": "00-見ました",
                "users": [
                    "U06L9S67MEJ"
                ],
                "count": 1
            }
        ]
    },
    {
        "user": "U06M7ST2WTA",
        "type": "message",
        "ts": "1726389171.497979",
        "client_msg_id": "4BBDAF1C-D1BD-4EF6-A48C-5B29FD1B49AA",
        "text": "冠婚葬祭のため欠席します。",
        "team": "T06L90YHJF8",
        "user_team": "T06L90YHJF8",
        "source_team": "T06L90YHJF8",
        "user_profile": {
            "avatar_hash": "401b878c66b6",
            "image_72": "https:\/\/avatars.slack-edge.com\/2024-06-24\/7324376365812_401b878c66b6ca6bef85_72.png",
            "first_name": "冨山真花",
            "real_name": "冨山真花",
            "display_name": "Tomiyama.Shinka",
            "team": "T06L90YHJF8",
            "name": "1020shinka",
            "is_restricted": false,
            "is_ultra_restricted": false
        },
        "thread_ts": "1726382194.260959",
        "parent_user_id": "U06L9S67MEJ",
        "blocks": [
            {
                "type": "rich_text",
                "block_id": "jl3l\/",
                "elements": [
                    {
                        "type": "rich_text_section",
                        "elements": [
                            {
                                "type": "text",
                                "text": "冠婚葬祭のため欠席します。"
                            }
                        ]
                    }
                ]
            }
        ],
        "reactions": [
            {
                "name": "00-見ました",
                "users": [
                    "U06L9S67MEJ"
                ],
                "count": 1
            }
        ]
    },
    {
        "user": "U070Y9UPJG3",
        "type": "message",
        "ts": "1726397069.983359",
        "client_msg_id": "7EE80AE5-88B1-45B2-B495-75619E213159",
        "text": "帰省するため欠席します。何度もすみません :woman-bowing::skin-tone-2: ",
        "team": "T06L90YHJF8",
        "user_team": "T06L90YHJF8",
        "source_team": "T06L90YHJF8",
        "user_profile": {
            "avatar_hash": "4ce8d7593494",
            "image_72": "https:\/\/avatars.slack-edge.com\/2024-11-13\/8021871334531_4ce8d7593494ec0c7664_72.png",
            "first_name": "富山歩咲",
            "real_name": "富山歩咲",
            "display_name": "Tomiyama. Ayusa",
            "team": "T06L90YHJF8",
            "name": "ayusa0915",
            "is_restricted": false,
            "is_ultra_restricted": false
        },
        "thread_ts": "1726382194.260959",
        "parent_user_id": "U06L9S67MEJ",
        "blocks": [
            {
                "type": "rich_text",
                "block_id": "MIEIm",
                "elements": [
                    {
                        "type": "rich_text_section",
                        "elements": [
                            {
                                "type": "text",
                                "text": "帰省するため欠席します。何度もすみません "
                            },
                            {
                                "type": "emoji",
                                "name": "woman-bowing",
                                "unicode": "1f647-1f3fb-200d-2640-fe0f",
                                "skin_tone": 2
                            },
                            {
                                "type": "text",
                                "text": " "
                            }
                        ]
                    }
                ]
            }
        ],
        "reactions": [
            {
                "name": "00-見ました",
                "users": [
                    "U06L9S67MEJ"
                ],
                "count": 1
            }
        ]
    },
    {
        "user": "U06M7SUSYNL",
        "type": "message",
        "ts": "1726426974.774369",
        "client_msg_id": "F57D2E29-5515-45DB-9644-C74349366E17",
        "text": "1人で小田急ロマンスカーに乗って御殿場行こうかなとか考えてたところです、連れて行ってください",
        "team": "T06L90YHJF8",
        "user_team": "T06L90YHJF8",
        "source_team": "T06L90YHJF8",
        "user_profile": {
            "avatar_hash": "91c7a30b3d91",
            "image_72": "https:\/\/avatars.slack-edge.com\/2024-02-28\/6709208137046_91c7a30b3d91571a135f_72.png",
            "first_name": "齋藤",
            "real_name": "齋藤 和",
            "display_name": "Saito.Nodoka",
            "team": "T06L90YHJF8",
            "name": "non.s1108",
            "is_restricted": false,
            "is_ultra_restricted": false
        },
        "thread_ts": "1726382194.260959",
        "parent_user_id": "U06L9S67MEJ",
        "blocks": [
            {
                "type": "rich_text",
                "block_id": "7YyxK",
                "elements": [
                    {
                        "type": "rich_text_section",
                        "elements": [
                            {
                                "type": "text",
                                "text": "1人で小田急ロマンスカーに乗って御殿場行こうかなとか考えてたところです、連れて行ってください"
                            }
                        ]
                    }
                ]
            }
        ],
        "reactions": [
            {
                "name": "00-見ました",
                "users": [
                    "U06L9S67MEJ"
                ],
                "count": 1
            }
        ]
    },
    {
        "user": "U070VFRN7PX",
        "type": "message",
        "ts": "1726466085.528989",
        "client_msg_id": "36D48544-6327-412B-91A4-69F8CFA6524C",
        "text": "旅行中のため欠席します。すみません。",
        "team": "T06L90YHJF8",
        "user_team": "T06L90YHJF8",
        "source_team": "T06L90YHJF8",
        "user_profile": {
            "avatar_hash": "15cce351931b",
            "image_72": "https:\/\/avatars.slack-edge.com\/2024-11-01\/7966829305810_15cce351931b99f69ada_72.png",
            "first_name": "横田清佳",
            "real_name": "横田清佳",
            "display_name": "Yokota.Sayaka",
            "team": "T06L90YHJF8",
            "name": "bonsoir.sayaka25",
            "is_restricted": false,
            "is_ultra_restricted": false
        },
        "thread_ts": "1726382194.260959",
        "parent_user_id": "U06L9S67MEJ",
        "blocks": [
            {
                "type": "rich_text",
                "block_id": "DT25V",
                "elements": [
                    {
                        "type": "rich_text_section",
                        "elements": [
                            {
                                "type": "text",
                                "text": "旅行中のため欠席します。すみません。"
                            }
                        ]
                    }
                ]
            }
        ],
        "reactions": [
            {
                "name": "00-見ました",
                "users": [
                    "U06L9S67MEJ"
                ],
                "count": 1
            }
        ]
    }
]