[
    {
        "user": "U06LK0FUAHZ",
        "type": "message",
        "ts": "1728197022.907999",
        "client_msg_id": "fdabd9c1-5c07-4591-8c17-ba197f8f5667",
        "text": "*<!channel>*\n1008 第23回運営局インフラ整備部門会議\n【時間】\n19 : 00 ~ 20 : 40\n【場所】\nLS406\n【持ち物】\n*パソコン、イヤホン*\n【議題】（時間はあくまでも目安です）\n1.各種報告（意思共有）（5分）\n2.部門記録を練習しよう！（意思共有）（30分）\n3.ごみ箱ナンバリング（意思共有）（30～40分）\n4.諸連絡（意思共有）（5分）\n\n確認したらリアクションを！！！！\n遅刻・欠席・早退は部門長に理由を添えて連絡！\n（←なるべく休まないようにしよう！！！！！！）\n\n20：40って書いてあるけどたぶんもうちょい早く終わります。\n今週からごみ・水場講習会がんばってくよ～！！",
        "team": "T06L90YHJF8",
        "user_team": "T06L90YHJF8",
        "source_team": "T06L90YHJF8",
        "user_profile": {
            "avatar_hash": "6e0b846c4968",
            "image_72": "https:\/\/avatars.slack-edge.com\/2024-11-28\/8120586451088_6e0b846c49682f74cad1_72.png",
            "first_name": "和田直樹",
            "real_name": "和田直樹",
            "display_name": "Wada.Naoki",
            "team": "T06L90YHJF8",
            "name": "nao.wadaaa0703",
            "is_restricted": false,
            "is_ultra_restricted": false
        },
        "blocks": [
            {
                "type": "rich_text",
                "block_id": "3mUAY",
                "elements": [
                    {
                        "type": "rich_text_section",
                        "elements": [
                            {
                                "type": "broadcast",
                                "range": "channel",
                                "style": {
                                    "bold": true
                                }
                            },
                            {
                                "type": "text",
                                "text": "\n1008 第23回運営局インフラ整備部門会議\n【時間】\n19 : 00 ~ 20 : 40\n【場所】\nLS406\n【持ち物】\n"
                            },
                            {
                                "type": "text",
                                "text": "パソコン、イヤホン",
                                "style": {
                                    "bold": true
                                }
                            },
                            {
                                "type": "text",
                                "text": "\n【議題】（時間はあくまでも目安です）\n1.各種報告（意思共有）（5分）\n2.部門記録を練習しよう！（意思共有）（30分）\n3.ごみ箱ナンバリング（意思共有）（30～40分）\n4.諸連絡（意思共有）（5分）\n\n確認したらリアクションを！！！！\n遅刻・欠席・早退は部門長に理由を添えて連絡！\n（←なるべく休まないようにしよう！！！！！！）\n\n20：40って書いてあるけどたぶんもうちょい早く終わります。\n今週からごみ・水場講習会がんばってくよ～！！"
                            }
                        ]
                    }
                ]
            }
        ],
        "reactions": [
            {
                "name": "00-otsukaresamadesu",
                "users": [
                    "U071B3AKPPT",
                    "U06LG66Q84D",
                    "U06LK5HCSE6",
                    "U06LG61QB3P",
                    "U070HS3D85D",
                    "U070YD8A2EN",
                    "U06LM2P58KC",
                    "U06ME05BLJW",
                    "U070HS7MJH5",
                    "U06LEAGKTSS",
                    "U071B3C838R",
                    "U070Y9TREE7"
                ],
                "count": 12
            },
            {
                "name": "運営_インフラ_やや転びなおき",
                "users": [
                    "U071B3AKPPT",
                    "U06LK5HCSE6",
                    "U070HS3D85D",
                    "U070HS7MJH5",
                    "U06LK3LKR9Q",
                    "U070Y9TREE7"
                ],
                "count": 6
            },
            {
                "name": "00-otsukare",
                "users": [
                    "U06LK5HCSE6"
                ],
                "count": 1
            },
            {
                "name": "猫ミーム-ぱくぱく",
                "users": [
                    "U06LK5HCSE6"
                ],
                "count": 1
            },
            {
                "name": "運営_あんじゅ_あいよー",
                "users": [
                    "U06LK3LKR9Q"
                ],
                "count": 1
            },
            {
                "name": "1限png",
                "users": [
                    "U06LK3LKR9Q"
                ],
                "count": 1
            },
            {
                "name": "00-見ました",
                "users": [
                    "U06LK3LKR9Q"
                ],
                "count": 1
            }
        ]
    }
]