[
    {
        "text": "<!channel>\nお疲れ様です。広報局1年の木室です。\n\n0226_第1回広報局会議議事録を\nOneDrive＞自分のファイル＞各局＞04_広報局＞01_局会議＞02_議事録＞2月＞0226にアップロードしました。\n\n議題は\n1.諸連絡（意思共有）\n2.広報局の考え方（意思共有）\n3.継続の心得（意思共有）\n4.グループワーク講座（意見交換）\n5.報連相ゲーム（意思共有）\nとなっております。\n\n提出が遅れてしまい大変申し訳ありませんでした。ご確認よろしくお願いします。",
        "files": [
            {
                "id": "F06N23F0821",
                "mode": "hidden_by_limit"
            }
        ],
        "upload": false,
        "user": "U06L4GN8N3Z",
        "display_as_bot": false,
        "blocks": [
            {
                "type": "rich_text",
                "block_id": "BN9Q4",
                "elements": [
                    {
                        "type": "rich_text_section",
                        "elements": [
                            {
                                "type": "broadcast",
                                "range": "channel"
                            },
                            {
                                "type": "text",
                                "text": "\nお疲れ様です。広報局1年の木室です。\n\n0226_第1回広報局会議議事録を\nOneDrive＞自分のファイル＞各局＞04_広報局＞01_局会議＞02_議事録＞2月＞0226にアップロードしました。\n\n議題は\n1.諸連絡（意思共有）\n2.広報局の考え方（意思共有）\n3.継続の心得（意思共有）\n4.グループワーク講座（意見交換）\n5.報連相ゲーム（意思共有）\nとなっております。\n\n提出が遅れてしまい大変申し訳ありませんでした。ご確認よろしくお願いします。"
                            }
                        ]
                    }
                ]
            }
        ],
        "type": "message",
        "ts": "1709712721.692879",
        "client_msg_id": "c3436047-43f4-48ed-ad7b-8408f17d18d4",
        "reactions": [
            {
                "name": "猫ミーム-ぱくぱく",
                "users": [
                    "U06LK3LMEPL",
                    "U06LXNY8KMF",
                    "U06LJBVA2DS",
                    "U06LK3HUVTL",
                    "U06LK3KA09G",
                    "U06L4GJBJP9"
                ],
                "count": 6
            },
            {
                "name": "00-otsukare",
                "users": [
                    "U06LK3LMEPL",
                    "U06LXNY8KMF",
                    "U06LCVDE88N",
                    "U06LK0EBWRH",
                    "U06LK3L6B4J",
                    "U06LVK2FU1X",
                    "U06LK3HUVTL",
                    "U06LCE9HTP0",
                    "U06LK3KA09G",
                    "U06L4GJBJP9",
                    "U06LY5XNLBT",
                    "U06LG60SFEH"
                ],
                "count": 12
            },
            {
                "name": "ななえ",
                "users": [
                    "U06LK3LMEPL",
                    "U06LXNY8KMF",
                    "U06LK3HUVTL",
                    "U06LK3KA09G",
                    "U06L4GJBJP9",
                    "U06LG60SFEH"
                ],
                "count": 6
            },
            {
                "name": "かの-暫定15単位",
                "users": [
                    "U06LK3LMEPL",
                    "U06LK3KA09G"
                ],
                "count": 2
            },
            {
                "name": "うごくたきもん",
                "users": [
                    "U06LXNY8KMF",
                    "U06LK3KA09G"
                ],
                "count": 2
            },
            {
                "name": "猫ミーム-チピチピチャパチャパ",
                "users": [
                    "U06LXNY8KMF",
                    "U06LK3KA09G"
                ],
                "count": 2
            },
            {
                "name": "不憫を継ぐきどこう",
                "users": [
                    "U06LCVDE88N",
                    "U06LK3KA09G",
                    "U06LXNY8KMF"
                ],
                "count": 3
            },
            {
                "name": "再履きど",
                "users": [
                    "U06LCVDE88N",
                    "U06LK3KA09G",
                    "U06LXNY8KMF",
                    "U06LY5XNLBT"
                ],
                "count": 4
            },
            {
                "name": "ハッピー",
                "users": [
                    "U06LK0EBWRH",
                    "U06LK3KA09G"
                ],
                "count": 2
            },
            {
                "name": "猫ミーム-ハッピーハッピーハッピー",
                "users": [
                    "U06LK3KA09G"
                ],
                "count": 1
            }
        ]
    }
]