[
    {
        "user": "U06LCUTBMU5",
        "type": "message",
        "ts": "1719993042.811579",
        "edited": {
            "user": "U06LCUTBMU5",
            "ts": "1720194880.000000"
        },
        "client_msg_id": "DCE16189-53EB-4E59-B2D1-E83EB07CC8C3",
        "text": "【7月期総会のお知らせ】\n<!channel> \nお疲れ様です。\n副委員長の橋本です。\n7月期総会についてご連絡します。\n出欠に関して、以下のフォームより全員回答してください。\n欠席・遅刻・早退する人は理由を明記してください。\n<https:\/\/forms.gle\/u1RBVUUczzAUBgfS8|https:\/\/forms.gle\/u1RBVUUczzAUBgfS8>\n【日時】\n7月6日(土) 13：00〜16：30（予定）\n【場所】\n第一校舎211教室\n※教室は12：30より入ることができます。\n【議題（予定）】\n1．各局報告\n2．全体合宿について\n3．縦割りコンテンツ（演出局・制作局）",
        "team": "T06L90YHJF8",
        "user_team": "T06L90YHJF8",
        "source_team": "T06L90YHJF8",
        "user_profile": {
            "avatar_hash": "d29ad1ed3aec",
            "image_72": "https:\/\/avatars.slack-edge.com\/2024-07-17\/7460050079888_d29ad1ed3aec69aa085e_72.png",
            "first_name": "橋本悠佑",
            "real_name": "橋本悠佑",
            "display_name": "Hashimoto.Yusuke",
            "team": "T06L90YHJF8",
            "name": "yusuke.h.1312",
            "is_restricted": false,
            "is_ultra_restricted": false
        },
        "attachments": [
            {
                "image_url": "https:\/\/lh5.googleusercontent.com\/LNFvyZFqh0ddR8DDoVM2u9hGKETjyiBBnYmbfVOl6wznXzvwcxg_8HqmOPVviHNcPB8i3CP2HK8",
                "image_width": 800,
                "image_height": 600,
                "image_bytes": 24483,
                "from_url": "https:\/\/forms.gle\/u1RBVUUczzAUBgfS8",
                "service_icon": "http:\/\/ssl.gstatic.com\/docs\/forms\/device_home\/ios_120.png",
                "id": 1,
                "original_url": "https:\/\/forms.gle\/u1RBVUUczzAUBgfS8",
                "fallback": "Google Docs: 7月期総会出欠フォーム",
                "title": "7月期総会出欠フォーム",
                "title_link": "https:\/\/forms.gle\/u1RBVUUczzAUBgfS8",
                "service_name": "Google Docs"
            }
        ],
        "blocks": [
            {
                "type": "rich_text",
                "block_id": "IWJFz",
                "elements": [
                    {
                        "type": "rich_text_section",
                        "elements": [
                            {
                                "type": "text",
                                "text": "【7月期総会のお知らせ】\n"
                            },
                            {
                                "type": "broadcast",
                                "range": "channel"
                            },
                            {
                                "type": "text",
                                "text": " \nお疲れ様です。\n副委員長の橋本です。\n7月期総会についてご連絡します。\n出欠に関して、以下のフォームより全員回答してください。\n欠席・遅刻・早退する人は理由を明記してください。\n"
                            },
                            {
                                "type": "link",
                                "url": "https:\/\/forms.gle\/u1RBVUUczzAUBgfS8",
                                "text": "https:\/\/forms.gle\/u1RBVUUczzAUBgfS8"
                            },
                            {
                                "type": "text",
                                "text": "\n【日時】\n7月6日(土) 13：00〜16：30（予定）\n【場所】\n第一校舎211教室\n※教室は12：30より入ることができます。\n【議題（予定）】\n1．各局報告\n2．全体合宿について"
                            },
                            {
                                "type": "text",
                                "text": "\n",
                                "style": {
                                    "bold": false,
                                    "italic": false,
                                    "strike": true
                                }
                            },
                            {
                                "type": "text",
                                "text": "3．縦割りコンテンツ（演出局・制作局）"
                            }
                        ]
                    }
                ]
            }
        ],
        "reactions": [
            {
                "name": "00-otsukaresamadesu",
                "users": [
                    "U06LCE9NLP8",
                    "U0710T3MCUC",
                    "U06LCED6ZK8",
                    "U06LJ4HJLMS",
                    "U06LK0FUAHZ",
                    "U06LK5HCSE6",
                    "U070YD778SE",
                    "U06L4GLJVKR",
                    "U06LGHETAFP",
                    "U070HS31CP9",
                    "U070VFY94H3",
                    "U070VFTRR61",
                    "U06LMH9MBFW",
                    "U071B38HAM7",
                    "U06LXR4BPS5",
                    "U06L4GH3T7H",
                    "U06L4GM463H",
                    "U06LK3MF9FC",
                    "U070VFQKEH3",
                    "U06M7TE180Y",
                    "U06LG610ADB",
                    "U071B3AKPPT",
                    "U071M740R32",
                    "U06M7SETDKJ",
                    "U06L9S67MEJ",
                    "U06L4CMKY8P",
                    "U071B3C838R",
                    "U06LK0DLEQ3",
                    "U06L2CSPXV5",
                    "U06LCE7DY6S",
                    "U06LXNYCLJV",
                    "U070HS3G355",
                    "U071M6ZVDMW",
                    "U070Y9S389Z",
                    "U070RQ167FG",
                    "U06LJ0SKMEZ",
                    "U06LM0QJV3L",
                    "U06LG61QB3P",
                    "U06LMGM3CG4",
                    "U06LCE69DRU",
                    "U06LK0E89MH",
                    "U06LCE8L8LW",
                    "U070RQ20K8W"
                ],
                "count": 43
            }
        ]
    }
]