[
    {
        "text": "縦割り班分け！",
        "files": [
            {
                "id": "F07AUSYKANT",
                "mode": "hidden_by_limit"
            }
        ],
        "upload": false,
        "user": "U06LKEPTCA0",
        "display_as_bot": false,
        "blocks": [
            {
                "type": "rich_text",
                "block_id": "bSRQd",
                "elements": [
                    {
                        "type": "rich_text_section",
                        "elements": [
                            {
                                "type": "text",
                                "text": "縦割り班分け！"
                            }
                        ]
                    }
                ]
            }
        ],
        "type": "message",
        "ts": "1720239610.742859",
        "client_msg_id": "098cfb6e-d878-4484-bda4-805af3707f70"
    }
]