[
    {
        "text": "<!channel>\nお疲れ様です。\n運営局インフラ整備部門の今井です。\n0321第7回運営局会議議事録を\nOneDrive＞自分のファイル＞各局＞01_運営局＞04_議事録＞局会議＞3月にアップロードしました。\n\n議題は\n1.各種報告（意思共有）\n2.理念・方針・ビジョンについて（意見交換）\n3.キャンデザを決めようの回④（意見交換・決定）\n4.諸連絡（意思共有）\nです。\nご確認お願いします。\n\n私は花粉症なのですが、今年の2月はマスクなしでも全く症状がでなかったんです。だから「もしかして私花粉症克服した？」と思って、何も対策をしてなかったんですが、3月に入ったら無事に花粉で鼻とかが死にました。\nスギ花粉のピークは3月下旬までらしいので、花粉症の仲間はあと少しの間一緒に頑張りましょう！",
        "files": [
            {
                "id": "F06RFH2CW0H",
                "mode": "hidden_by_limit"
            }
        ],
        "upload": false,
        "user": "U06LCE7DY6S",
        "display_as_bot": false,
        "blocks": [
            {
                "type": "rich_text",
                "block_id": "EROp+",
                "elements": [
                    {
                        "type": "rich_text_section",
                        "elements": [
                            {
                                "type": "broadcast",
                                "range": "channel"
                            },
                            {
                                "type": "text",
                                "text": "\nお疲れ様です。\n運営局インフラ整備部門の今井です。\n0321第7回運営局会議議事録を\nOneDrive＞自分のファイル＞各局＞01_運営局＞04_議事録＞局会議＞3月にアップロードしました。\n\n議題は\n1.各種報告（意思共有）\n2.理念・方針・ビジョンについて（意見交換）\n3.キャンデザを決めようの回④（意見交換・決定）\n4.諸連絡（意思共有）\nです。\nご確認お願いします。\n\n私は花粉症なのですが、今年の2月はマスクなしでも全く症状がでなかったんです。だから「もしかして私花粉症克服した？」と思って、何も対策をしてなかったんですが、3月に入ったら無事に花粉で鼻とかが死にました。\nスギ花粉のピークは3月下旬までらしいので、花粉症の仲間はあと少しの間一緒に頑張りましょう！"
                            }
                        ]
                    }
                ]
            }
        ],
        "type": "message",
        "ts": "1711324805.813359",
        "client_msg_id": "de68ba50-a6b2-483a-b3fe-ad8e36a7de4b",
        "reactions": [
            {
                "name": "00-otsukaresamadesu",
                "users": [
                    "U06L4GHLP2B",
                    "U06LEAGKTSS",
                    "U06LK0FUAHZ",
                    "U06LG66LXAR",
                    "U06LK3MMALA",
                    "U06LM2P58KC",
                    "U06ME05BLJW",
                    "U06LK0FC935",
                    "U06LK5HCSE6",
                    "U06LK0EQS59",
                    "U06LKJS20KC",
                    "U06M7SX52RW",
                    "U06M7SQPKL0",
                    "U06L4GHAANB",
                    "U06LMH8Q2TW"
                ],
                "count": 15
            },
            {
                "name": "運営_チームインフラno1",
                "users": [
                    "U06LK0FUAHZ",
                    "U06LM2P58KC",
                    "U06L4H8CGQP",
                    "U06ME05BLJW",
                    "U06LK0FC935",
                    "U06LK5HCSE6",
                    "U06LK0EQS59",
                    "U06LK3LHG0J"
                ],
                "count": 8
            },
            {
                "name": "00-otsukare",
                "users": [
                    "U06L97X3V6J",
                    "U06LK3LHG0J"
                ],
                "count": 2
            },
            {
                "name": "運営_あんじゅ_あいよー",
                "users": [
                    "U06LK3LKR9Q"
                ],
                "count": 1
            },
            {
                "name": "001_運営_局長",
                "users": [
                    "U06LKHN3RE0"
                ],
                "count": 1
            }
        ]
    },
    {
        "text": "<!channel>\nお疲れ様です。\n運営局インフラ整備部門の川口です。\n0322_第1回インフラ整備部門会議議事録をOneDrive＞自分のファイル＞各局＞01_運営局＞04_議事録＞インフラ整備部門会議＞3月にアップロードしました。\n\n議題は、\n1. 部門内の係を決めよう！(意見交換・決定)\n2. 今年度のインフラ整備部門について(意思共有)\n3. 部門定義について(意見交換・決定)\n4. 部門方針について(意見交換・決定)\n5. 諸連絡(意思決定)\nです。\nご確認よろしくお願いします。\n\n今回が局、部門通じて自身初の議事録でした！まさかここまでお預けされるとは思ってなかったです。今更ながら議事録の洗礼を受けました。継続にもなってこんなにも敲かれて正直恥ずかしいです、、、ながしゅんもめいも出すの早くてほんと尊敬します。\nそんなことより口座の残高が家賃と水道光熱費差し引いて50円になっちまいました。発熱も相まって頭が痛いです。おすすめの単発バイトあったら教えてほしいです。",
        "files": [
            {
                "id": "F06QXDGLKUN",
                "mode": "hidden_by_limit"
            }
        ],
        "upload": false,
        "user": "U06LG61QB3P",
        "display_as_bot": false,
        "blocks": [
            {
                "type": "rich_text",
                "block_id": "10E7K",
                "elements": [
                    {
                        "type": "rich_text_section",
                        "elements": [
                            {
                                "type": "broadcast",
                                "range": "channel"
                            },
                            {
                                "type": "text",
                                "text": "\nお疲れ様です。\n運営局インフラ整備部門の川口です。\n0322_第1回インフラ整備部門会議議事録をOneDrive＞自分のファイル＞各局＞01_運営局＞04_議事録＞インフラ整備部門会議＞3月にアップロードしました。\n\n議題は、\n1. 部門内の係を決めよう！(意見交換・決定)\n2. 今年度のインフラ整備部門について(意思共有)\n3. 部門定義について(意見交換・決定)\n4. 部門方針について(意見交換・決定)\n5. 諸連絡(意思決定)\nです。\nご確認よろしくお願いします。\n\n今回が局、部門通じて自身初の議事録でした！まさかここまでお預けされるとは思ってなかったです。今更ながら議事録の洗礼を受けました。継続にもなってこんなにも敲かれて正直恥ずかしいです、、、ながしゅんもめいも出すの早くてほんと尊敬します。\nそんなことより口座の残高が家賃と水道光熱費差し引いて50円になっちまいました。発熱も相まって頭が痛いです。おすすめの単発バイトあったら教えてほしいです。"
                            }
                        ]
                    }
                ]
            }
        ],
        "type": "message",
        "ts": "1711349792.961079",
        "edited": {
            "user": "U06LG61QB3P",
            "ts": "1711379103.000000"
        },
        "client_msg_id": "c187aba0-cffe-42c1-b513-16883bef8557",
        "reactions": [
            {
                "name": "00-otsukaresamadesu",
                "users": [
                    "U06LEAGKTSS",
                    "U06LK5HCSE6",
                    "U06LG61PW7P",
                    "U06LK0FC935",
                    "U06LK3MMALA",
                    "U06LK0EQS59",
                    "U06LM2P58KC",
                    "U06LK3MRV98",
                    "U06LK0FUAHZ",
                    "U06L4GHLP2B",
                    "U06LKJS20KC",
                    "U06M7SX52RW",
                    "U06ME05BLJW",
                    "U06M7SQPKL0",
                    "U06LG62V1FX",
                    "U06L4GHAANB",
                    "U06LMH8Q2TW"
                ],
                "count": 17
            },
            {
                "name": "運営_インフラ_チームインフラ",
                "users": [
                    "U06L4H8CGQP",
                    "U06LK0FC935",
                    "U06LCE7DY6S",
                    "U06LK3MMALA",
                    "U06LM2P58KC",
                    "U06LK3LHG0J",
                    "U06ME05BLJW",
                    "U06LG62V1FX"
                ],
                "count": 8
            },
            {
                "name": "運営_チームインフラno1",
                "users": [
                    "U06LK0EQS59",
                    "U06LM2P58KC",
                    "U06ME05BLJW"
                ],
                "count": 3
            },
            {
                "name": "001_運営_局長",
                "users": [
                    "U06LKHN3RE0"
                ],
                "count": 1
            }
        ]
    }
]